{
  "users": [
    {
      "name": "Karla Tovar",
      "ci": "22324234",
      "birthday": "ejsfejsfes",
      "email": "ricardo@gmail.com",
      "phone": "214234234",
      "organization": "adawa",
      "id": 2
    },
    {
      "name": "Angel Navarro",
      "ci": "1732932123",
      "birthday": "2020-10-17",
      "email": "angel@email.com",
      "phone": "213423424",
      "organization": "1",
      "id": 4
    },
    {
      "name": "Angelica Quero",
      "ci": "21123456",
      "birthday": "1994-06-06",
      "email": "angelicaquero@email.com",
      "phone": "21332312",
      "organization": "3",
      "id": 5
    },
    {
      "name": "Carmen",
      "ci": "532fsfs",
      "birthday": "2020-09-29",
      "email": "carmen@gmail.com",
      "phone": "111111",
      "organization": "2",
      "id": 6
    },
    {
      "name": "fsefse",
      "ci": "fsfse",
      "birthday": "2020-10-01",
      "email": "esfs@email.com",
      "phone": "3242342",
      "organization": "2",
      "id": 9
    },
    {
      "name": "dawdwa",
      "ci": "dawda",
      "birthday": "2020-10-07",
      "email": "ric@e",
      "phone": "2423",
      "organization": "2",
      "id": 10
    }
  ],
  "organizations": [
    {
      "id": 1,
      "name": "Organizaci贸n 1"
    },
    {
      "id": 2,
      "name": "Organizaci贸n 2"
    },
    {
      "id": 3,
      "name": "Organizaci贸n 3"
    },
    {
      "id": 4,
      "name": "Organizaci贸n 4"
    }
  ]
}